LICENSE.txt
MANIFEST.in
README.rst
setup.py
sdl2/SDL2.pxd
sdl2/SDL2_image.pxd
sdl2/SDL2_mixer.pxd
sdl2/SDL2_ttf.pxd
sdl2/__init__.py
sdl2_cython.egg-info/PKG-INFO
sdl2_cython.egg-info/SOURCES.txt
sdl2_cython.egg-info/dependency_links.txt
sdl2_cython.egg-info/top_level.txt