Metadata-Version: 1.0
Name: sdl2_cython
Version: 0.2.1
Summary: Cython PXD files for SDL2
Home-page: http://bitbucket.org/tgjones/sdl2_cython
Author: Tim Jones
Author-email: tgjonesuk@gmail.com
License: The MIT License (MIT)
